{"file_path": "Source/BasketBallGame/Variant_Platforming/Animation/AnimNotify_EndDash.cpp", "file_id": "Source_BasketBallGame_Variant_Platforming_Animation_AnimNotify_EndDash_cpp", "asset_path": "", "doc_id": "qq-cce4fb52-d5ad-42c6-a0c6-f659f9329092", "referencers": [], "dependencies": [], "content": "// Copyright Epic Games, Inc. All Rights Reserved.\n\n\n#include \"AnimNotify_EndDash.h\"\n#include \"PlatformingCharacter.h\"\n#include \"Components/SkeletalMeshComponent.h\"\n\nvoid UAnimNotify_EndDash::Notify(USkeletalMeshComponent* MeshComp, UAnimSequenceBase* Animation, const FAnimNotifyEventReference& EventReference)\n{\n\t// cast the owner to the attacker interface\n\tif (APlatformingCharacter* PlatformingCharacter = Cast<APlatformingCharacter>(MeshComp->GetOwner()))\n\t{\n\t\t// tell the actor to end the dash\n\t\tPlatformingCharacter->EndDash();\n\t}\n}\n\nFString UAnimNotify_EndDash::GetNotifyName_Implementation() const\n{\n\treturn FString(\"End Dash\");\n}\n"}